pypmp/__init__.py
pypmp/pypmp.py
pypmp-0.3.0.post1.dist-info/LICENSE
pypmp-0.3.0.post1.dist-info/WHEEL
pypmp-0.3.0.post1.dist-info/METADATA
pypmp-0.3.0.post1.dist-info/RECORD
