Metadata-Version: 2.1
Name: pypmp
Version: 0.3.0.post1
Summary: Python lib to interact with ManageEngine Password Manager Pro's REST API
Home-page: https://github.com/post-luxembourg/pypmp
License: GPL-3.0-only
Author: Philipp Schmitt
Author-email: philipp.schmitt@post.lu
Requires-Python: >=3.7,<4.0
Classifier: License :: OSI Approved :: GNU General Public License v3 (GPLv3)
Classifier: Programming Language :: Python :: 3
Classifier: Programming Language :: Python :: 3.7
Classifier: Programming Language :: Python :: 3.8
Classifier: Programming Language :: Python :: 3.9
Requires-Dist: requests (>=2.25.1,<3.0.0)
Project-URL: Repository, https://github.com/post-luxembourg/pypmp
